majormode/__init__.py
majormode/perseus/__init__.py
majormode/perseus/client/__init__.py
majormode/perseus/client/api.py
majormode/perseus/client/service/__init__.py
majormode/perseus/client/service/account/__init__.py
majormode/perseus/client/service/account/account_service.py
majormode/perseus/client/service/area/__init__.py
majormode/perseus/client/service/area/area_service.py
majormode/perseus/client/service/base_service.py
majormode/perseus/client/service/category/__init__.py
majormode/perseus/client/service/category/category_service.py
majormode/perseus/client/service/notification/__init__.py
majormode/perseus/client/service/notification/notification_service.py
majormode/perseus/client/service/social/__init__.py
majormode/perseus/client/service/social/social_service.py
majormode/perseus/client/service/team/__init__.py
majormode/perseus/client/service/team/team_service.py
majormode/perseus/client/service/team/test/__init__.py
majormode/perseus/client/service/team/test/team_service_unittest.py
majormode/perseus/client/unittest/__init__.py
majormode/perseus/client/unittest/base_unittest.py
perseus_restful_api_client_library-1.4.12.dist-info/LICENSE.md
perseus_restful_api_client_library-1.4.12.dist-info/WHEEL
perseus_restful_api_client_library-1.4.12.dist-info/METADATA
perseus_restful_api_client_library-1.4.12.dist-info/RECORD
