Metadata-Version: 2.1
Name: perseus-restful-api-client-library
Version: 1.4.12
Summary: Perseus RESTful API Client Python Library
Home-page: https://github.com/majormode/perseus-restful-api-client-python-library
License: see LICENSE.md
Keywords: perseus,resful,api,server,framework
Author: Daniel CAUNE
Author-email: daniel.caune@gmail.com
Requires-Python: >=3.9,<4.0
Classifier: Development Status :: 5 - Production/Stable
Classifier: License :: Other/Proprietary License
Classifier: Operating System :: OS Independent
Classifier: Programming Language :: Python
Classifier: Programming Language :: Python :: 3
Classifier: Programming Language :: Python :: 3.9
Classifier: Programming Language :: Python :: 3.10
Classifier: Programming Language :: Python :: 3.11
Classifier: Topic :: Software Development :: Libraries
Requires-Dist: perseus-core-library (>=1.19,<2.0)
Requires-Dist: requests (>=2.31.0,<3.0.0)
Requires-Dist: urllib3 (>=2.2.1,<3.0.0)
Project-URL: Repository, https://github.com/majormode/perseus-restful-api-client-python-library
